piecrust/__init__.py
piecrust/__version__.py
piecrust/app.py
piecrust/appconfig.py
piecrust/appconfigdefaults.py
piecrust/cache.py
piecrust/chefutil.py
piecrust/configuration.py
piecrust/environment.py
piecrust/events.py
piecrust/fastpickle.py
piecrust/main.py
piecrust/osutil.py
piecrust/page.py
piecrust/pathutil.py
piecrust/rendering.py
piecrust/routing.py
piecrust/uriutil.py
piecrust/workerpool.py
piecrust/admin/__init__.py
piecrust/admin/bcryptfallback.py
piecrust/admin/blueprint.py
piecrust/admin/pubutil.py
piecrust/admin/settings.py
piecrust/admin/siteinfo.py
piecrust/admin/textutil.py
piecrust/admin/web.py
piecrust/admin/assets/img/apple-touch-icon.png
piecrust/admin/assets/img/foodtruck.png
piecrust/admin/assets/js/foodtruck.js
piecrust/admin/assets/raw/foodtruck.psd
piecrust/admin/assets/sass/foodtruck.scss
piecrust/admin/assets/sass/foodtruck/_base.scss
piecrust/admin/assets/sass/foodtruck/_dashboard.scss
piecrust/admin/assets/sass/foodtruck/_editing.scss
piecrust/admin/assets/sass/foodtruck/_publog.scss
piecrust/admin/assets/sass/foodtruck/_sidebar.scss
piecrust/admin/scm/__init__.py
piecrust/admin/scm/base.py
piecrust/admin/scm/git.py
piecrust/admin/scm/mercurial.py
piecrust/admin/static/css/foodtruck.min.css
piecrust/admin/static/fonts/glyphicons-halflings-regular.eot
piecrust/admin/static/fonts/glyphicons-halflings-regular.svg
piecrust/admin/static/fonts/glyphicons-halflings-regular.ttf
piecrust/admin/static/fonts/glyphicons-halflings-regular.woff
piecrust/admin/static/fonts/glyphicons-halflings-regular.woff2
piecrust/admin/static/fonts/ionicons.eot
piecrust/admin/static/fonts/ionicons.svg
piecrust/admin/static/fonts/ionicons.ttf
piecrust/admin/static/fonts/ionicons.woff
piecrust/admin/static/fonts/open-iconic.eot
piecrust/admin/static/fonts/open-iconic.otf
piecrust/admin/static/fonts/open-iconic.svg
piecrust/admin/static/fonts/open-iconic.ttf
piecrust/admin/static/fonts/open-iconic.woff
piecrust/admin/static/img/apple-touch-icon.png
PieCrust-3.3.0.dist-info/LICENSE.rst
PieCrust-3.3.0.dist-info/METADATA
PieCrust-3.3.0.dist-info/WHEEL
PieCrust-3.3.0.dist-info/entry_points.txt
PieCrust-3.3.0.dist-info/top_level.txt
PieCrust-3.3.0.dist-info/RECORD
