Metadata-Version: 2.1
Name: PieCrust
Version: 3.3.0
Summary: A powerful static website generator and lightweight CMS.
Home-page: http://bolt80.com/piecrust
Author: Ludovic Chabant
Author-email: ludovic@chabant.com
License: Apache License 2.0
Keywords: python website generator blog portfolio gallery cms
Platform: UNKNOWN
Classifier: Development Status :: 4 - Beta
Classifier: License :: OSI Approved :: Apache Software License
Classifier: Environment :: Console
Classifier: Intended Audience :: Developers
Classifier: Intended Audience :: System Administrators
Classifier: Natural Language :: English
Classifier: Operating System :: MacOS :: MacOS X
Classifier: Operating System :: POSIX :: Linux
Classifier: Operating System :: Microsoft :: Windows
Classifier: Programming Language :: Python :: 3 :: Only
Classifier: Topic :: Internet :: WWW/HTTP :: Site Management
Requires-Dist: beautifulsoup4 (>=4.7.0)
Requires-Dist: colorama (>=0.4.0)
Requires-Dist: compressinja (>=0.0.2)
Requires-Dist: Flask-IndieAuth (>=0.0.3.2)
Requires-Dist: Flask-Login (>=0.4.1)
Requires-Dist: Flask (>=1.0.2)
Requires-Dist: Inukshuk (>=0.1.2)
Requires-Dist: Jinja2 (>=2.10.1)
Requires-Dist: Markdown (>=3.1)
Requires-Dist: MarkupSafe (>=1.1)
Requires-Dist: mf2py (>=1.1.2)
Requires-Dist: paramiko (>=2.4.2)
Requires-Dist: Pillow (>=6.0.0)
Requires-Dist: Pygments (>=2.2.0)
Requires-Dist: pystache (>=0.5.4)
Requires-Dist: python-dateutil (>=2.8)
Requires-Dist: PyYAML (>=5.1)
Requires-Dist: repoze.lru (>=0.7)
Requires-Dist: requests (>=2.21.0)
Requires-Dist: smartypants (>=2.0.1)
Requires-Dist: strict-rfc3339 (>=0.7)
Requires-Dist: textile (>=3.0.3)
Requires-Dist: Unidecode (>=1.0.23)
Requires-Dist: watchdog (>=0.9.0)
Requires-Dist: Werkzeug (>=0.15.2)
